pyiron_gpl/__init__.py
pyiron_gpl/_version.py
pyiron_gpl/elastic/__init__.py
pyiron_gpl/elastic/elastic.py
pyiron_gpl/gaussian/__init__.py
pyiron_gpl/gaussian/gaussian.py
pyiron_gpl/nma/__init__.py
pyiron_gpl/nma/nma.py
pyiron_gpl/quickff/__init__.py
pyiron_gpl/quickff/quickff.py
pyiron_gpl/yaff/__init__.py
pyiron_gpl/yaff/yaff.py
pyiron_gpl-0.0.5.dist-info/LICENSE
pyiron_gpl-0.0.5.dist-info/METADATA
pyiron_gpl-0.0.5.dist-info/WHEEL
pyiron_gpl-0.0.5.dist-info/top_level.txt
pyiron_gpl-0.0.5.dist-info/RECORD
