Metadata-Version: 2.1
Name: pyiron-gpl
Version: 0.0.5
Summary: pyiron - an integrated development environment (IDE) for computational materials science.
Home-page: https://github.com/pyiron/pyiron_gpl
Author: Max-Planck-Institut für Eisenforschung GmbH - Computational Materials Design (CM) Department
Author-email: janssen@mpie.de
License: GPLv3
Keywords: pyiron
Classifier: Development Status :: 5 - Production/Stable
Classifier: Topic :: Scientific/Engineering :: Physics
Classifier: License :: OSI Approved :: BSD License
Classifier: Intended Audience :: Science/Research
Classifier: Operating System :: OS Independent
Classifier: Programming Language :: Python :: 3.9
Classifier: Programming Language :: Python :: 3.10
Classifier: Programming Language :: Python :: 3.11
License-File: LICENSE
Requires-Dist: molmod >=1.4.8
Requires-Dist: numpy >=1.26.4
Requires-Dist: atomistics >=0.1.24
Requires-Dist: pyiron-atomistics >=0.5.0
Requires-Dist: spglib >=2.3.1
Requires-Dist: scipy >=1.12.0
Requires-Dist: quickff >=2.2.4
Requires-Dist: tamkin >=1.2.6
Requires-Dist: yaff >=1.6.0
